audioset_strong_download/Downloader.py
audioset_strong_download/__init__.py
audioset_strong_download-2.0.5.dist-info/LICENSE
audioset_strong_download-2.0.5.dist-info/METADATA
audioset_strong_download-2.0.5.dist-info/WHEEL
audioset_strong_download-2.0.5.dist-info/top_level.txt
audioset_strong_download-2.0.5.dist-info/RECORD
