Metadata-Version: 2.1
Name: audioset-strong-download
Version: 2.0.5
Summary: This package aims at simplifying the download of the strong version of AudioSet dataset. This is a revised version of audioset-download (https://github.com/MorenoLaQuatra/audioset-download).
Home-page: https://github.com/curlsloth/audioset-strong-download
Author: Andrew Chang & Moreno La Quatra
Author-email: c.andrew123@gmail.com
Classifier: Operating System :: OS Independent
Classifier: License :: OSI Approved :: GNU General Public License v3 (GPLv3)
Classifier: Programming Language :: Python :: 3.9
Classifier: Programming Language :: Python :: 3.8
Classifier: Programming Language :: Python :: 3.7
Classifier: Programming Language :: Python :: 3
License-File: LICENSE
Requires-Dist: ffmpeg==1.4
Requires-Dist: joblib
Requires-Dist: pandas
Requires-Dist: yt-dlp>=2024.12.6
Requires-Dist: numpy
Provides-Extra: dev
Requires-Dist: pytest>=3.7; extra == "dev"
